README.md
setup.py
git_timewarp/__init__.py
git_timewarp/time_warp.py
git_timewarp.egg-info/PKG-INFO
git_timewarp.egg-info/SOURCES.txt
git_timewarp.egg-info/dependency_links.txt
git_timewarp.egg-info/top_level.txt