Metadata-Version: 2.1
Name: git-timewarp
Version: 0.0.2
Summary: time travel to a previous git commit
Home-page: https://github.com/mixarcid/git-timewarp
Author: Michael Arcidiacono
Author-email: 
License: UNKNOWN
Platform: UNKNOWN
Classifier: Programming Language :: Python :: 3
Classifier: Operating System :: OS Independent
Requires-Python: >=3.6
